cli_agent/__init__.py
cli_agent/get_api_key.py
cli_agent/main.py
cli_agent/tools.py
py_cli_agent-0.1.4.dist-info/licenses/LICENSE
py_cli_agent-0.1.4.dist-info/METADATA
py_cli_agent-0.1.4.dist-info/WHEEL
py_cli_agent-0.1.4.dist-info/entry_points.txt
py_cli_agent-0.1.4.dist-info/top_level.txt
py_cli_agent-0.1.4.dist-info/RECORD
