Metadata-Version: 2.4
Name: py-cli-agent
Version: 0.1.4
Summary: A CLI Agent powered by Gemini AI
Author-email: Andro <androkingdom1@gmail.com>
Project-URL: Homepage, https://github.com/andro-dev/cli-agent
Project-URL: Bug Tracker, https://github.com/andro-dev/cli-agent/issues
License-File: LICENSE
Requires-Dist: openai
Requires-Dist: rich
Requires-Dist: python-dotenv
Dynamic: license-file
